{
    "asreviewVersion": "1.2",
    "apiVersion": "1.1.2",
    "data": {
        "items": [
            {
                "id": "recall",
                "title": "Recall",
                "value": [
                    [
                        0.1,
                        0.972972972972973
                    ],
                    [
                        0.25,
                        1.0
                    ],
                    [
                        0.5,
                        1.0
                    ],
                    [
                        0.75,
                        1.0
                    ],
                    [
                        0.9,
                        1.0
                    ]
                ]
            },
            {
                "id": "wss",
                "title": "Work Saved over Sampling",
                "value": [
                    [
                        0.95,
                        0.8930068387381425
                    ]
                ]
            },
            {
                "id": "erf",
                "title": "Extra Relevant record Found",
                "value": [
                    [
                        0.1,
                        0.8648648648648649
                    ]
                ]
            },
            {
                "id": "atd",
                "title": "Average time to discovery",
                "value": 102.86486486486487
            },
            {
                "id": "td",
                "title": "Time to discovery",
                "value": [
                    [
                        2545,
                        1
                    ],
                    [
                        902,
                        23
                    ],
                    [
                        1746,
                        25
                    ],
                    [
                        4461,
                        28
                    ],
                    [
                        3769,
                        32
                    ],
                    [
                        3680,
                        43
                    ],
                    [
                        767,
                        48
                    ],
                    [
                        462,
                        50
                    ],
                    [
                        2496,
                        58
                    ],
                    [
                        1248,
                        63
                    ],
                    [
                        2624,
                        68
                    ],
                    [
                        953,
                        72
                    ],
                    [
                        3842,
                        73
                    ],
                    [
                        116,
                        75
                    ],
                    [
                        1356,
                        77
                    ],
                    [
                        3076,
                        78
                    ],
                    [
                        2803,
                        79
                    ],
                    [
                        4377,
                        83
                    ],
                    [
                        4327,
                        88
                    ],
                    [
                        1994,
                        89
                    ],
                    [
                        831,
                        91
                    ],
                    [
                        4154,
                        93
                    ],
                    [
                        4269,
                        94
                    ],
                    [
                        3608,
                        95
                    ],
                    [
                        1554,
                        96
                    ],
                    [
                        2279,
                        98
                    ],
                    [
                        1033,
                        99
                    ],
                    [
                        1180,
                        100
                    ],
                    [
                        730,
                        107
                    ],
                    [
                        51,
                        109
                    ],
                    [
                        4201,
                        111
                    ],
                    [
                        1514,
                        128
                    ],
                    [
                        2740,
                        133
                    ],
                    [
                        3314,
                        155
                    ],
                    [
                        1429,
                        179
                    ],
                    [
                        1565,
                        320
                    ],
                    [
                        3442,
                        645
                    ]
                ]
            }
        ]
    }
}